httpget/__init__.py
httpget/wget.py
httpget-1.1.0.dist-info/WHEEL
httpget-1.1.0.dist-info/METADATA
httpget-1.1.0.dist-info/RECORD
