Metadata-Version: 2.1
Name: httpget
Version: 1.1.0
Summary: Download files using http
Author: Wissem Mansouri
Author-email: wissem.mansouri.ing@gmail.com
Requires-Python: >=3.8,<4.0
Classifier: Programming Language :: Python :: 3
Classifier: Programming Language :: Python :: 3.10
Classifier: Programming Language :: Python :: 3.8
Classifier: Programming Language :: Python :: 3.9
Requires-Dist: flake8 (>=4.0.1,<5.0.0)
Requires-Dist: requests (>=2.27.1,<3.0.0)
Requires-Dist: tqdm (>=4.62.3,<5.0.0)
